rusty_runways-3.0.2.dist-info/METADATA
rusty_runways-3.0.2.dist-info/WHEEL
rusty_runways/__init__.py
rusty_runways/gym_env.py
rusty_runways_py/__init__.py
rusty_runways_py/rusty_runways_py.abi3.so
rusty_runways-3.0.2.dist-info/RECORD
