Metadata-Version: 2.4
Name: rusty-runways
Version: 3.0.2
Classifier: Programming Language :: Python
Classifier: Programming Language :: Python :: 3
Classifier: Programming Language :: Python :: 3 :: Only
Classifier: Programming Language :: Python :: 3.8
Classifier: Programming Language :: Python :: 3.9
Classifier: Programming Language :: Python :: 3.10
Classifier: Programming Language :: Python :: 3.11
Classifier: Programming Language :: Python :: 3.12
Classifier: License :: OSI Approved :: MIT License
Classifier: Operating System :: OS Independent
Requires-Dist: gymnasium>=0.29,<1.0 ; extra == 'gym'
Provides-Extra: gym
Summary: Python bindings for Rusty Runways
Keywords: rust,simulation,logistics,reinforcement-learning,gymnasium,rl,ai,ml
Author: RustyRunways Authors
License: MIT
Requires-Python: >=3.8
Project-URL: Homepage, https://github.com/DennisLent/RustyRunways
Project-URL: Documentation, https://dennislent.github.io/RustyRunways
Project-URL: Source, https://github.com/DennisLent/RustyRunways
Project-URL: Issues, https://github.com/DennisLent/RustyRunways/issues
